musamusa_fal/aboutproject.py
musamusa_fal/fal.py
musamusa_fal-0.1.6.dist-info/LICENSE
musamusa_fal-0.1.6.dist-info/WHEEL
musamusa_fal-0.1.6.dist-info/METADATA
musamusa_fal-0.1.6.dist-info/RECORD
