Metadata-Version: 2.1
Name: musamusa-fal
Version: 0.1.6
Summary: Use this package to store a filename and a line number.
License: GPLv3
Author: suizokukan
Author-email: suizokukan@orange.fr
Requires-Python: >=3.9,<4.0
Classifier: License :: Other/Proprietary License
Classifier: Programming Language :: Python :: 3
Classifier: Programming Language :: Python :: 3.9
Requires-Dist: iaswn (>=0.0.7,<0.0.8)
Requires-Dist: rich (>=10.2.0,<11.0.0)
